pop/__init__.py
pop/__main__.py
pop/p/__init__.py
pop/p/bt-nc.py
pop/p/bt-node.py
pop/p/bt-php.py
pop/p/bt-py.py
pop/p/enc-php-b64.py
pop/p/enc-php-dec.py
pop/p/enc-php-hex.py
pop/p/enc-php-oct.py
pop/p/enc-py-b64.py
pop/p/enc-py-dec.py
pop/p/enc-py-hex.py
pop/p/enc-sh-b64.py
pop/p/enc-sh-dec.py
pop/p/enc-sh-hex.py
pop/p/enc-sh-oct.py
pop/p/img-png-comment.py
pop/p/img-png-tail.py
pop/p/ns-bash.py
pop/p/ns-cpio.py
pop/p/ns-getent.py
pop/p/ns-gtar.py
pop/p/ns-logger.py
pop/p/ns-mtgnu.py
pop/p/ns-ping.py
pop/p/ns-pl.py
pop/p/ns-py.py
pop/p/ns-route.py
pop/p/ns-ss.py
pop/p/ns-ssh.py
pop/p/ns-systemctl.py
pop/p/rc-cosmo.py
pop/p/rc-curl-sh.py
pop/p/rc-nc-sh.py
pop/p/rc-nim.py
pop/p/rc-node.py
pop/p/rc-openssl-sh.py
pop/p/rc-php.py
pop/p/rc-py.py
pop/p/rc-wget-sh.py
pop/p/rh-morbol.py
pop/p/rt-bash.py
pop/p/rt-cosmo.py
pop/p/rt-go.py
pop/p/rt-nc.py
pop/p/rt-nim.py
pop/p/rt-node.py
pop/p/rt-openssl.py
pop/p/rt-php.py
pop/p/rt-pl.py
pop/p/rt-ps.py
pop/p/rt-py.py
pop/p/ru-py.py
pop/p/ws-jsp-get.py
pop/p/ws-php-get.py
pop/p/ws-php-post.py
pop/p/xd-bash.py
pop/p/xd-cpio.py
pop/p/xd-getent.py
pop/p/xd-gtar.py
pop/p/xd-logger.py
pop/p/xd-mtgnu.py
pop/p/xd-ping.py
pop/p/xd-py.py
pop/p/xd-route.py
pop/p/xd-ss.py
pop/p/xd-ssh.py
pop/p/xd-systemctl.py
pop/static/favicon.png
pop/templates/index.html
popsh-1.0.3.data/scripts/pop
popsh-1.0.3.dist-info/LICENSE.txt
popsh-1.0.3.dist-info/METADATA
popsh-1.0.3.dist-info/WHEEL
popsh-1.0.3.dist-info/top_level.txt
popsh-1.0.3.dist-info/RECORD
