Metadata-Version: 2.1
Name: popsh
Version: 1.0.3
Summary: An offensive payload generator.
Home-page: https://gitlab.com/pgregoire/pop
Author: Philippe Grégoire
Author-email: git@pgregoire.xyz
Project-URL: Bug Tracker, https://gitlab.com/pgregoire/pop/issues
Classifier: Programming Language :: Python :: 3
Classifier: License :: OSI Approved :: GNU General Public License v2 (GPLv2)
Classifier: Operating System :: OS Independent
Requires-Python: >=3.6
License-File: LICENSE.txt
Requires-Dist: Pillow (==9.0.1)
